LICENSE
MANIFEST.in
README.rst
pyproject.toml
setup.cfg
setup.py
eo_forge/VERSION
eo_forge/__init__.py
eo_forge.egg-info/PKG-INFO
eo_forge.egg-info/SOURCES.txt
eo_forge.egg-info/dependency_links.txt
eo_forge.egg-info/requires.txt
eo_forge.egg-info/top_level.txt
eo_forge/io/GenLoader.py
eo_forge/io/LandsatLoaders.py
eo_forge/io/SentinelLoaders.py
eo_forge/io/__init__.py
eo_forge/utils/__init__.py
eo_forge/utils/downloader.py
eo_forge/utils/landsat.py
eo_forge/utils/raster_utils.py
eo_forge/utils/sentinel.py
eo_forge/utils/shapes.py
eo_forge/utils/utils.py
examples/eo-forge-gcp-downloader.ipynb
examples/eo-forge-loaders-101-Loggers.ipynb
examples/eo-forge-loaders-101.ipynb
examples/eo-forge-loaders-102.ipynb
examples/eo-forge-loaders-103.ipynb
examples/important_logs.log
examples/important_logs2.log