Metadata-Version: 2.1
Name: eo-forge
Version: 0.3.2
Summary: Python tools for remote sensing data processing.
Home-page: https://github.com/EO-Forge/eo-forge.git
Author: Felix Rojo Lapalma, Andrés Pérez Hortal
License: UNKNOWN
Platform: UNKNOWN
Classifier: Development Status :: 4 - Beta
Classifier: License :: OSI Approved :: BSD License
Classifier: Programming Language :: Python :: 3
Classifier: Operating System :: OS Independent
Requires-Python: >=3.7
License-File: LICENSE
